{
    "m@g.c": {
        "1": {
            "details": "bong",
            "end": "2/11/2010",
            "start": "2/10/2010",
            "target": "20000",
            "title": "bang"
        },
        "2": {
            "details": "log",
            "end": "3/10/2010",
            "start": "2/10/2010",
            "target": "20000",
            "title": "hog"
        }
    },
    "m2@g.c": {
        "1": {
            "details": "bong",
            "end": "2/11/2010",
            "start": "2/10/2010",
            "target": "20000",
            "title": "bang"
        },
        "2": {
            "details": "log",
            "end": "3/10/2010",
            "start": "2/10/2010",
            "target": "20000",
            "title": "hog"
        }
    }
}